patentsberta/__init__.py
patentsberta/patentsberta_classification.py
patent_classification-0.0.5.dist-info/METADATA
patent_classification-0.0.5.dist-info/WHEEL
patent_classification-0.0.5.dist-info/top_level.txt
patent_classification-0.0.5.dist-info/RECORD
