Metadata-Version: 2.1
Name: patent-classification
Version: 0.0.5
Summary: Patent Classification
Home-page: UNKNOWN
Author: AI-Growth-Lab
Author-email: hamidb@business.aau.dk
License: UNKNOWN
Keywords: python,first package
Platform: UNKNOWN
Classifier: Development Status :: 3 - Alpha
Classifier: Intended Audience :: Education
Classifier: Programming Language :: Python :: 2
Classifier: Programming Language :: Python :: 3
Classifier: Operating System :: MacOS :: MacOS X
Classifier: Operating System :: Microsoft :: Windows
